pytaxapi/__init__.py
pytaxapi/client.py
pytaxapi/errors.py
pytaxapi/models.py
pytaxapi-0.1.2.dist-info/METADATA
pytaxapi-0.1.2.dist-info/WHEEL
pytaxapi-0.1.2.dist-info/RECORD
