Metadata-Version: 2.4
Name: pytaxapi
Version: 0.1.2
Summary: Асинхронная библиотека Python для отправки чеков в приложении Мой Налог
Requires-Python: >=3.10
Requires-Dist: httpx>=0.28.1
Provides-Extra: dev
Requires-Dist: build; extra == 'dev'
Requires-Dist: mypy; extra == 'dev'
Requires-Dist: pytest; extra == 'dev'
Requires-Dist: ruff; extra == 'dev'
Requires-Dist: twine; extra == 'dev'
